MANIFEST.in
README.md
setup.py
preggy/__init__.py
preggy/__main__.py
preggy/__meta__.py
preggy/core.py
preggy/utils.py
preggy.egg-info/PKG-INFO
preggy.egg-info/SOURCES.txt
preggy.egg-info/dependency_links.txt
preggy.egg-info/requires.txt
preggy.egg-info/top_level.txt
preggy/assertions/__init__.py
preggy/assertions/comparison.py
preggy/assertions/emptiness.py
preggy/assertions/equality.py
preggy/assertions/inclusion.py
preggy/assertions/length.py
preggy/assertions/like.py
preggy/assertions/types/__init__.py
preggy/assertions/types/boolean.py
preggy/assertions/types/classes.py
preggy/assertions/types/errors.py
preggy/assertions/types/file.py
preggy/assertions/types/function.py
preggy/assertions/types/nullable.py
preggy/assertions/types/numeric.py
preggy/assertions/types/regexp.py
tests/__init__.py
tests/test_be_here.py
tests/test_chaining.py
tests/test_comparison.py
tests/test_emptiness.py
tests/test_equality.py
tests/test_inclusion.py
tests/test_length.py
tests/test_like.py
tests/types/__init__.py
tests/types/test_boolean.py
tests/types/test_classes.py
tests/types/test_errors.py
tests/types/test_file.py
tests/types/test_function.py
tests/types/test_nullable.py
tests/types/test_numeric.py
tests/types/test_regexp.py